resize_and_crop/__init__.py
resize_and_crop/main.py
resize_and_crop/utils.py
resize_and_crop-0.1.1.dist-info/METADATA
resize_and_crop-0.1.1.dist-info/RECORD
resize_and_crop-0.1.1.dist-info/WHEEL
resize_and_crop-0.1.1.dist-info/top_level.txt
